README.md
setup.py
hive_tagbot.egg-info/PKG-INFO
hive_tagbot.egg-info/SOURCES.txt
hive_tagbot.egg-info/dependency_links.txt
hive_tagbot.egg-info/entry_points.txt
hive_tagbot.egg-info/requires.txt
hive_tagbot.egg-info/top_level.txt
tagbot/bot.py
tagbot/utils.py