Metadata-Version: 1.0
Name: hive-tagbot
Version: 0.1.1
Summary: Random upvote bot on specific tags on HIVE network
Home-page: http://github.com/emre/tagbot
Author: emre yilmaz
Author-email: mail@emreyilmaz.me
License: MIT
Platform: UNKNOWN
